MANIFEST.in
README.md
requirements.txt
setup.py
news_popularity_prediction/__init__.py
news_popularity_prediction.egg-info/PKG-INFO
news_popularity_prediction.egg-info/SOURCES.txt
news_popularity_prediction.egg-info/dependency_links.txt
news_popularity_prediction.egg-info/entry_points.txt
news_popularity_prediction.egg-info/requires.txt
news_popularity_prediction.egg-info/top_level.txt
news_popularity_prediction/datautil/__init__.py
news_popularity_prediction/datautil/common.py
news_popularity_prediction/datautil/feature_rw.py
news_popularity_prediction/entry_points/__init__.py
news_popularity_prediction/entry_points/snow_2016_workshop/__init__.py
news_popularity_prediction/entry_points/snow_2016_workshop/barrapunto_entry.py
news_popularity_prediction/entry_points/snow_2016_workshop/reddit_news_entry.py
news_popularity_prediction/entry_points/snow_2016_workshop/run_all_experiments.py
news_popularity_prediction/entry_points/snow_2016_workshop/slashdot_entry.py
news_popularity_prediction/features/__init__.py
news_popularity_prediction/features/basic.py
news_popularity_prediction/features/basic_wrappers.py
news_popularity_prediction/features/branching.py
news_popularity_prediction/features/branching_wrappers.py
news_popularity_prediction/features/common.py
news_popularity_prediction/features/intermediate.py
news_popularity_prediction/features/temporal.py
news_popularity_prediction/features/temporal_wrappers.py
news_popularity_prediction/features/user_graph.py
news_popularity_prediction/features/user_graph_wrappers.py
news_popularity_prediction/learning/__init__.py
news_popularity_prediction/learning/cascade_lifetime.py
news_popularity_prediction/learning/concatenate_features.py
news_popularity_prediction/learning/ranking.py
news_popularity_prediction/learning/single_experiment.py
news_popularity_prediction/vizualization/__init__.py