Metadata-Version: 1.1
Name: news-popularity-prediction
Version: 0.1.1
Summary: A set of methods that predict the future values of popularity indices for news posts using a variety of features.
Home-page: https://github.com/MKLab-ITI/news-popularity-prediction
Author: Georgios Rizos
Author-email: georgerizos@iti.gr
License: Apache
Keywords: news-popularity-prediction online-discussion-analysis Reveal-FP7
Platform: UNKNOWN
Classifier: Development Status :: 2 - Pre-Alpha
Classifier: Intended Audience :: Science/Research
Classifier: License :: OSI Approved :: Apache Software License
Classifier: Natural Language :: English
Classifier: Operating System :: Unix
Classifier: Programming Language :: Python
Classifier: Programming Language :: Python :: 3
Classifier: Programming Language :: Python :: 3.3
Classifier: Programming Language :: Python :: 3.4
Classifier: Programming Language :: Python :: 3 :: Only
Classifier: Programming Language :: Python :: Implementation
Classifier: Programming Language :: Python :: Implementation :: CPython
Classifier: Topic :: Scientific/Engineering :: Information Analysis
